bitmapmaker/__init__.py
bitmapmaker/bitmap.py
bitmapmaker/bitmapgui.py
bitmapmaker-1.0.3.dist-info/METADATA
bitmapmaker-1.0.3.dist-info/WHEEL
bitmapmaker-1.0.3.dist-info/licenses/LICENSE
bitmapmaker-1.0.3.dist-info/RECORD
