Metadata-Version: 2.4
Name: bitmapmaker
Version: 1.0.3
Summary: A package for creating your own custom bitmaps from a windows GUI.
Project-URL: Homepage, https://github.com/Ruxton07/bitmapmaker
Project-URL: Issues, https://github.com/Ruxton07/bitmapmaker/issues
Author-email: Ryan Kellar <rt.kellar@gmail.com>
License-File: LICENSE
Classifier: License :: OSI Approved :: MIT License
Classifier: Operating System :: Microsoft :: Windows
Classifier: Programming Language :: Python :: 3
Requires-Python: >=3.8
